mrun/__init__.py
mrun/main.py
nrun/__init.py__
nrun/main.py
melisa_marian-0.1.0.dist-info/METADATA
melisa_marian-0.1.0.dist-info/WHEEL
melisa_marian-0.1.0.dist-info/entry_points.txt
melisa_marian-0.1.0.dist-info/RECORD
