Metadata-Version: 2.4
Name: melisa_marian
Version: 0.1.0
Summary: A CLI tool to run commands and send ntfy notifications.
Author-email: Your Name <your@email.com>
Classifier: Environment :: Console
Classifier: License :: OSI Approved :: MIT License
Classifier: Operating System :: OS Independent
Classifier: Programming Language :: Python :: 3
Classifier: Topic :: System :: Monitoring
Classifier: Topic :: Utilities
Requires-Python: >=3.7
Requires-Dist: numpy>=1.21.6
Requires-Dist: pandas>=1.1.5
Requires-Dist: requests>=2.20
